aspio/__init__.py
aspio/asp.py
aspio/errors.py
aspio/input.py
aspio/output.py
aspio/parser.py
aspio/program.py
aspio/registry.py
aspio/helper/__init__.py
aspio/helper/caching_iterable.py
aspio/helper/filesystem_ipc.py
aspio/helper/stream_capture_thread.py
aspio/helper/typing.py
aspio/solver/__init__.py
aspio/solver/abc.py
aspio/solver/dlvhex2.py
aspio-0.0.1.dist-info/DESCRIPTION.rst
aspio-0.0.1.dist-info/METADATA
aspio-0.0.1.dist-info/RECORD
aspio-0.0.1.dist-info/WHEEL
aspio-0.0.1.dist-info/metadata.json
aspio-0.0.1.dist-info/top_level.txt
